README.md
setup.py
yaphue/__init__.py
yaphue/bridge.py
yaphue/light.py
yaphue.egg-info/PKG-INFO
yaphue.egg-info/SOURCES.txt
yaphue.egg-info/dependency_links.txt
yaphue.egg-info/requires.txt
yaphue.egg-info/top_level.txt