Metadata-Version: 1.0
Name: yaphue
Version: 0.1.1
Summary: Yet Another Python / Philips Hue -library
Home-page: https://github.com/kipe/yaphue
Author: Kimmo Huoman
Author-email: kipenroskaposti@gmail.com
License: UNKNOWN
Platform: UNKNOWN
